alphafold/__init__.py
alphafold/analysis/__init__.py
alphafold/analysis/analyze_residue.py
alphafold/analysis/attention_pipeline.py
alphafold/analysis/plot_difference.py
alphafold/analysis/process_attention.py
alphafold/analysis/utils.py
alphafold/common/__init__.py
alphafold/common/confidence.py
alphafold/common/mmcif_metadata.py
alphafold/common/protein.py
alphafold/common/protein_test.py
alphafold/common/residue_constants.py
alphafold/common/residue_constants_test.py
alphafold/common/stereo_chemical_props.txt
alphafold/data/__init__.py
alphafold/data/feature_processing.py
alphafold/data/mmcif_parsing.py
alphafold/data/msa_identifiers.py
alphafold/data/msa_pairing.py
alphafold/data/parsers.py
alphafold/data/pipeline.py
alphafold/data/pipeline_multimer.py
alphafold/data/templates.py
alphafold/data/tools/__init__.py
alphafold/data/tools/hhblits.py
alphafold/data/tools/hhsearch.py
alphafold/data/tools/hmmbuild.py
alphafold/data/tools/hmmsearch.py
alphafold/data/tools/jackhmmer.py
alphafold/data/tools/kalign.py
alphafold/data/tools/utils.py
alphafold/model/__init__.py
alphafold/model/all_atom.py
alphafold/model/all_atom_multimer.py
alphafold/model/all_atom_test.py
alphafold/model/common_modules.py
alphafold/model/config.py
alphafold/model/data.py
alphafold/model/features.py
alphafold/model/folding.py
alphafold/model/folding_multimer.py
alphafold/model/geometry/__init__.py
alphafold/model/geometry/rigid_matrix_vector.py
alphafold/model/geometry/rotation_matrix.py
alphafold/model/geometry/struct_of_array.py
alphafold/model/geometry/test_utils.py
alphafold/model/geometry/utils.py
alphafold/model/geometry/vector.py
alphafold/model/layer_stack.py
alphafold/model/layer_stack_test.py
alphafold/model/lddt.py
alphafold/model/lddt_test.py
alphafold/model/mapping.py
alphafold/model/model.py
alphafold/model/modules.py
alphafold/model/modules_multimer.py
alphafold/model/prng.py
alphafold/model/prng_test.py
alphafold/model/quat_affine.py
alphafold/model/quat_affine_test.py
alphafold_attention-0.0.21.dist-info/METADATA
alphafold_attention-0.0.21.dist-info/WHEEL
alphafold_attention-0.0.21.dist-info/RECORD
